cosSim/__init__.py
cosSim/cli.py
cosSim/parseClass.py
cosSim/similarity.py
cosSim/text_preprocessor.py
cosSim/corpora/english.txt
cosSim/corpora/german.txt
cosSim-0.1.0.dist-info/LICENSE
cosSim-0.1.0.dist-info/METADATA
cosSim-0.1.0.dist-info/WHEEL
cosSim-0.1.0.dist-info/entry_points.txt
cosSim-0.1.0.dist-info/top_level.txt
cosSim-0.1.0.dist-info/RECORD
