Metadata-Version: 2.1
Name: cosSim
Version: 0.1.0
Summary: This CLI tool compares files or directories with cosine similarity.
Home-page: https://github.com/ovanov/cosSim
Author: ovanov
Author-email: ovanov@protonmail.com
License: MIT
Keywords: cosine Similarity,file comparison,nltk,CLI programm,vectorisation
Platform: any
Classifier: Development Status :: 3 - Alpha
Classifier: Intended Audience :: Developers
Classifier: Topic :: Software Development :: Build Tools
Classifier: License :: OSI Approved :: MIT License
Classifier: Programming Language :: Python :: 3
Classifier: Programming Language :: Python :: 3.6
Classifier: Programming Language :: Python :: 3.7
Classifier: Programming Language :: Python :: 3.8
Classifier: Programming Language :: Python :: 3.9
Requires-Python: >=3.6
License-File: LICENSE
Requires-Dist: nltk (>=3.6.2)
Requires-Dist: numpy (>=1.21.1)
